{
  "id": "zlib.nexacro-json-1.0.encode",
  "operation": "encode",
  "profile": "nexacro-json-1.0",
  "options": {
    "zlib": true
  },
  "value": {
    "parameters": [],
    "datasets": []
  },
  "expect": {
    "kind": "wire",
    "output": {
      "encoding": "base64",
      "data": "/614AQARAO7/eyJ2ZXJzaW9uIjoiMS4wIn0BAAD//zUhBVA="
    }
  },
  "source": {
    "repository": "xapi-conformance",
    "commit": "working-tree",
    "path": "vectors/roundtrip/zlib-nexacro-json-1-0-encode.json",
    "license": "repository"
  },
  "required": true
}
