{
  "id": "security.row-limit",
  "operation": "encode",
  "profile": "nexacro-json-1.0",
  "options": {
    "strict": true,
    "limits": {
      "rows": 0
    }
  },
  "value": {
    "parameters": [],
    "datasets": [
      {
        "id": "d",
        "columns": [],
        "constColumns": [],
        "rows": [
          {
            "type": "N",
            "orgRow": null,
            "values": {}
          }
        ]
      }
    ]
  },
  "expect": {
    "kind": "wire",
    "output": {
      "data": "eyJEYXRhc2V0cyI6W3siaWQiOiJkIiwiUm93cyI6W3siX1Jvd1R5cGVfIjoiTiJ9XX1dLCJ2ZXJzaW9uIjoiMS4wIn0=",
      "encoding": "base64"
    },
    "value": {
      "datasets": [
        {
          "columns": [],
          "constColumns": [],
          "id": "d",
          "rows": [
            {
              "orgRow": null,
              "type": "N",
              "values": {}
            }
          ]
        }
      ],
      "parameters": []
    }
  },
  "source": {
    "repository": "xapi-conformance",
    "commit": "working-tree",
    "path": "vectors/security/row-limit.json",
    "license": "repository"
  },
  "required": true
}
